LICENSE.txt
MANIFEST.in
README.md
setup.cfg
setup.py
inktool/__init__.py
inktool/api.py
inktool/config.py
inktool/constants/constants.py
inktool/endpoints/__init__.py
inktool/endpoints/base.py
inktool/endpoints/neprinters.py
inktool/endpoints/orders.py
inktool/models/__init__.py
inktool/models/base.py
inktool/models/neprinters.py
inktool/models/orders.py
inktool_wrapper.egg-info/PKG-INFO
inktool_wrapper.egg-info/SOURCES.txt
inktool_wrapper.egg-info/dependency_links.txt
inktool_wrapper.egg-info/requires.txt
inktool_wrapper.egg-info/top_level.txt