Metadata-Version: 2.1
Name: inktool-wrapper
Version: 0.2.0
Summary: Wrapper for the InkTool endpoints
Home-page: https://github.com/Ecosy-EU/inktool-wrapper
Author: Alexander Schillemans
Author-email: alexander.schillemans@lhs.global
License: GPL-3.0-or-later
Download-URL: https://github.com/Ecosy-EU/inktool-wrapper/archive/refs/tags/0.2.0.tar.gz
Keywords: inktool,cloudspot,spotgroup,wrapper
Platform: UNKNOWN
Classifier: Development Status :: 3 - Alpha
Classifier: Intended Audience :: Developers
Classifier: Topic :: Software Development :: Build Tools
Classifier: License :: OSI Approved :: GNU General Public License v3 or later (GPLv3+)
Classifier: Programming Language :: Python :: 3.6
